detectiq/__init__.py
detectiq/core/llm/__init__.py
detectiq/core/llm/base.py
detectiq/core/llm/sigma_rules.py
detectiq/core/llm/snort_rules.py
detectiq/core/llm/toolkits/__init__.py
detectiq/core/llm/toolkits/base.py
detectiq/core/llm/toolkits/prompts.py
detectiq/core/llm/toolkits/sigma_toolkit.py
detectiq/core/llm/toolkits/snort_toolkit.py
detectiq/core/llm/toolkits/yara_toolkit.py
detectiq/core/llm/tools/__init__.py
detectiq/core/llm/tools/sigma/__init__.py
detectiq/core/llm/tools/sigma/create_sigma_rule.py
detectiq/core/llm/tools/sigma/find_sigma_rule.py
detectiq/core/llm/tools/sigma/query_to_sigma_rule.py
detectiq/core/llm/tools/sigma/translate_sigma_rule.py
detectiq/core/llm/tools/snort/__init__.py
detectiq/core/llm/tools/snort/analyze_pcap.py
detectiq/core/llm/tools/snort/create_snort_rule.py
detectiq/core/llm/tools/snort/find_snort_rule.py
detectiq/core/llm/tools/yara/__init__.py
detectiq/core/llm/tools/yara/analyze_file.py
detectiq/core/llm/tools/yara/create_yara_rule.py
detectiq/core/llm/tools/yara/find_yara_rule.py
detectiq/core/llm/tools/yara/scan_file.py
detectiq/core/llm/yara_rules.py
detectiq/core/utils/logging.py
detectiq/core/utils/sigma/rule_updater.py
detectiq/core/utils/snort/analyzers/__init__.py
detectiq/core/utils/snort/analyzers/anomaly.py
detectiq/core/utils/snort/analyzers/base.py
detectiq/core/utils/snort/analyzers/content.py
detectiq/core/utils/snort/analyzers/http.py
detectiq/core/utils/snort/analyzers/protocol.py
detectiq/core/utils/snort/analyzers/threshold.py
detectiq/core/utils/snort/analyzers/whitelist.py
detectiq/core/utils/snort/pcap_analyzer.py
detectiq/core/utils/snort/rule_updater.py
detectiq/core/utils/yara/__init__.py
detectiq/core/utils/yara/config.py
detectiq/core/utils/yara/file_analyzer.py
detectiq/core/utils/yara/pe_analyzer.py
detectiq/core/utils/yara/rule_scanner.py
detectiq/core/utils/yara/rule_updater.py
detectiq/globals.py
detectiq/sigmaiq/.gitignore
detectiq/sigmaiq/__init__.py
detectiq/sigmaiq/backends/__init__.py
detectiq-0.1.47.dist-info/LICENSE
detectiq-0.1.47.dist-info/METADATA
detectiq-0.1.47.dist-info/WHEEL
detectiq-0.1.47.dist-info/entry_points.txt
detectiq-0.1.47.dist-info/RECORD
