Metadata-Version: 2.1
Name: detectiq
Version: 0.1.47
Summary: A detection engineering workbench with LLM capabilities, including SigmaIQ features
Home-page: https://github.com/AttackIQ/DetectIQ
License: LGPL-2.1
Keywords: security,detection,sigma,yara,snort,llm
Author: AttackIQ
Author-email: rajesh.sharma@attackiq.com
Requires-Python: >=3.9,<=3.12
Classifier: Development Status :: 4 - Beta
Classifier: Intended Audience :: Developers
Classifier: Intended Audience :: Information Technology
Classifier: License :: OSI Approved
Classifier: Programming Language :: Python :: 3
Classifier: Programming Language :: Python :: 3.9
Classifier: Programming Language :: Python :: 3.10
Classifier: Programming Language :: Python :: 3.11
Classifier: Programming Language :: Python :: 3.12
Classifier: Topic :: Security
Classifier: Topic :: Software Development :: Libraries :: Python Modules
Provides-Extra: elastic
Provides-Extra: microsoft
Provides-Extra: splunk
Requires-Dist: aiofiles (>=24.1.0,<25.0.0)
Requires-Dist: cryptography (>=42.0.5,<43.0.0)
Requires-Dist: dpkt (>=1.9.8,<2.0.0)
Requires-Dist: elasticsearch (>=8.0.0,<9.0.0) ; extra == "elastic"
Requires-Dist: faiss-cpu (>=1.9.0,<2.0.0)
Requires-Dist: idstools (>=0.6.5,<0.7.0)
Requires-Dist: importlib-resources ; python_version < "3.10"
Requires-Dist: keyring (>=25.5.0,<26.0.0)
Requires-Dist: langchain (>=0.3.7,<0.4.0)
Requires-Dist: langchain-community (>=0.3.7,<0.4.0)
Requires-Dist: langchain-core (>=0.3.17,<0.4.0)
Requires-Dist: langchain-openai (>=0.2.8,<0.3.0)
Requires-Dist: msal (>=1.31.1,<2.0.0) ; extra == "microsoft"
Requires-Dist: openai (>=1.54.4,<2.0.0)
Requires-Dist: pefile (>=2024.8.26,<2025.0.0)
Requires-Dist: plyara (>=2.1.1,<3.0.0)
Requires-Dist: pydantic (>=2.0.0)
Requires-Dist: pysigma (>=0.11.14,<0.12.0)
Requires-Dist: pysigma-backend-carbonblack (>=0.1.8,<0.2.0)
Requires-Dist: pysigma-backend-cortexxdr (>=0.1.4,<0.2.0)
Requires-Dist: pysigma-backend-crowdstrike (>=2.0.0,<3.0.0)
Requires-Dist: pysigma-backend-elasticsearch (>=1.1.2,<2.0.0)
Requires-Dist: pysigma-backend-insightidr (>=0.2.4,<0.3.0)
Requires-Dist: pysigma-backend-kusto (>=0.4.0,<0.5.0)
Requires-Dist: pysigma-backend-loki (>=0.12.0,<0.13.0)
Requires-Dist: pysigma-backend-netwitness (>=0.1.3,<0.2.0)
Requires-Dist: pysigma-backend-opensearch (>=1.0.2,<2.0.0)
Requires-Dist: pysigma-backend-qradar-aql (>=0.3.2,<0.4.0)
Requires-Dist: pysigma-backend-secops (==0.1.4)
Requires-Dist: pysigma-backend-sentinelone (>=0.1.3,<0.2.0)
Requires-Dist: pysigma-backend-splunk (>=1.1.0,<2.0.0)
Requires-Dist: pysigma-backend-stix2 (>=0.2.0,<0.3.0)
Requires-Dist: pysigma-pipeline-sysmon (>=1.0.4,<2.0.0)
Requires-Dist: pysigma-pipeline-windows (>=1.2.0,<2.0.0)
Requires-Dist: python-dotenv (>=1.0.1,<2.0.0)
Requires-Dist: python-magic (>=0.4.27,<0.5.0)
Requires-Dist: pyyaml (>=6.0,<7.0)
Requires-Dist: requests (>=2.32.3,<3.0.0)
Requires-Dist: ruamel-yaml (>=0.18.6,<0.19.0)
Requires-Dist: scapy (>=2.6.1,<3.0.0)
Requires-Dist: six
Requires-Dist: splunk-sdk (>=2.1.0,<3.0.0) ; extra == "splunk"
Requires-Dist: tiktoken (>=0.8.0,<0.9.0)
Requires-Dist: yara-python (>=4.5.1,<5.0.0)
Project-URL: Repository, https://github.com/AttackIQ/DetectIQ
